lemon_ai/__init__.py
lemon_ai/cito_api_wrapper.py
lemon_ai/cito_tool.py
lemon_ai/cito_toolkit.py
lemon_ai/cito_workflow.py
lemon_ai/execute_workflow.py
lemon_ai/get_integrations.py
lemon_ai-0.1.6.dist-info/LICENSE
lemon_ai-0.1.6.dist-info/METADATA
lemon_ai-0.1.6.dist-info/WHEEL
lemon_ai-0.1.6.dist-info/top_level.txt
lemon_ai-0.1.6.dist-info/RECORD
